Metadata-Version: 2.4
Name: mcp-server-bridge
Version: 0.1.0
Summary: MCP Bridge: A unified interface for CLI, HTTP, and LLM integration.
Author-email: zzczsczsvzsbsn <key99887@163.com>
License-File: LICENSE
Requires-Python: >=3.10
Requires-Dist: mcp[cli]>=1.24.0
Requires-Dist: platformdirs==4.5.1
Requires-Dist: pyyaml>=6.0.3
Requires-Dist: requests>=2.32.5
Provides-Extra: dev
Requires-Dist: pytest>=9.0.2; extra == 'dev'
